{
  "type": "EFFECT_REQUESTED",
  "recordedAt": "2026-03-02T19:14:03.836Z",
  "data": {
    "effectId": "01KJQZHJXC7NASGF1J31C98R59",
    "invocationKey": "transfer-tabs-feature:S000008:implement-2",
    "invocationHash": "010569c620fdc5d5554ba724b4b8e34b466ed61708c4855cf1e0b859da20496d",
    "stepId": "S000008",
    "taskId": "implement-2",
    "kind": "agent",
    "label": "Implement transfer tabs (iteration 2)",
    "taskDefRef": "tasks/01KJQZHJXC7NASGF1J31C98R59/task.json"
  },
  "checksum": "cb8e2a907697d9f81f0a58163829a8fbe39860b2d9436f8693d2e449f3a99d2b"
}
